{
  "name": {
    "hebrew": "מגדיאל מרקס",
    "english": "Magdiel Marquez",
    "spanish": "Magdiel Márquez",
    "japanese": "マグディエル・マルケス"
  },
  "title": {
    "hebrew": "מפתח האינטרנט המדהים",
    "japanese": "素晴らしいウェブ開発者",
    "english": "The amazing web developer",
    "spanish": "El increíble desarrollador web"
  },
  "links": [
    {
      "title": {
        "english": "Facebook",
        "spanish": "Facebook"
      },
      "link": "https://github.com/"
    },
    {
      "title": {
        "english": "Instagram",
        "spanish": "Instagram"
      },
      "link": "https://github.com/"
    },
    {
      "title": {
        "english": "Github",
        "spanish": "Github"
      },
      "link": "https://github.com/"
    }
  ]
}
